savida/__init__.py
savida/fixture.py
savida/server.py
savida-0.2.2.dist-info/LICENSE
savida-0.2.2.dist-info/METADATA
savida-0.2.2.dist-info/WHEEL
savida-0.2.2.dist-info/top_level.txt
savida-0.2.2.dist-info/RECORD
