Metadata-Version: 2.1
Name: savida
Version: 0.2.2
Summary: Savida - Testing HTTP Server Fixture
Home-page: https://github.com/shoppimon/savida
Author: Shahar Evron
Author-email: shahar@shoppimon.com
License: Apache 2.0
Keywords: http server testing fixture
Platform: UNKNOWN
Requires-Dist: Werkzeug
